{"collections_apps.md":"DwV25MG2","collections_bookmarks.md":"CusqES-S","essay_2017-07-08-moonlight-and-wine.md":"C4DpOY1p","essay_2017-08-18-lantern.md":"Ba3FUrxL","essay_2018-08-13-poem.md":"am6Z8TVN","essay_2019-10-25-reflection.md":"BjvodNaB","essay_2019-12-07-empathy.md":"CmWBE79n","essay_2020-02-20-hometown.md":"Bi1zD4O9","essay_2020-05-23-chaos.md":"DlQoXBGw","essay_2020-06-21-exit.md":"BHPek5jr","essay_2020-07-19-maze.md":"BzW-7F-f","essay_2020-08-15-nightwalker.md":"DHEdLk-0","essay_2020-08-20-time-witness.md":"BhdD0ON1","essay_2020-10-16-old-diary.md":"-0zR9bwk","essay_2020-11-22-balance.md":"C_cJE7ML","essay_2021-01-10-reflection.md":"Dmjedap7","essay_2021-01-31-infer.md":"CY4beuxU","essay_2021-02-20-wilderness.md":"hDGbSew6","essay_2021-02-26-impermanence.md":"Tx8YZnTH","essay_2021-03-17-poem.md":"kOnM2A3z","essay_2021-03-21-break-the-loop.md":"CFsPsN66","essay_2021-03-28-sakura-and-ferris-wheel.md":"DNGooFqr","essay_2021-08-14-autumn-dream.md":"7CCKtqWy","essay_2022-01-31-wandering.md":"CGxdw5YY","essay_2022-05-15-breeze.md":"B-l2rZ4J","essay_2022-09-12-telosma.md":"DHDomnr4","essay_2023-01-01-dusk-and-dawn.md":"C_nBFDRP","essay_2023-02-25-cat-and-fate.md":"N64u6Qio","essay_2023-05-16-poem.md":"Cba4MpHX","essay_2024-01-11-wander.md":"DduQLult","essay_index.md":"DGsqg2yL","index.md":"BNHqwkjv","leetcode_1.md":"DNtdeAIj","leetcode_100.md":"CNcscmxb","leetcode_101.md":"DW-9yZ5R","leetcode_1019.md":"4648pPXb","leetcode_102.md":"DNY5TCK4","leetcode_103.md":"BXBxIEB2","leetcode_104.md":"B-rb1TDw","leetcode_105.md":"BnNlcwmF","leetcode_106.md":"ovCOp9me","leetcode_107.md":"C4BTW9Tu","leetcode_108.md":"BKix9ryK","leetcode_109.md":"DKZoKWfx","leetcode_11.md":"BvGRSU3i","leetcode_110.md":"CWJ7Dq0t","leetcode_111.md":"CkiEqMZ3","leetcode_112.md":"D1MQ882k","leetcode_113.md":"DtFMlk4H","leetcode_114.md":"CzAh5Hwb","leetcode_115.md":"C4GwatLV","leetcode_116.md":"Do0Kpqj-","leetcode_117.md":"BKgcd3Sn","leetcode_1171.md":"oYj34ufW","leetcode_118.md":"Bu39lx22","leetcode_1185.md":"DrX90azK","leetcode_119.md":"Ca1qpsbV","leetcode_12.md":"CV1Zt_gd","leetcode_120.md":"B5_WcUgs","leetcode_1200.md":"RNMDM29C","leetcode_121.md":"0qhp-kXP","leetcode_122.md":"DpINYpHS","leetcode_1222.md":"CG-be_TZ","leetcode_1232.md":"GBU4M6j4","leetcode_125.md":"BjfjCeOL","leetcode_129.md":"Bmm85EQo","leetcode_1290.md":"CxkjqKXo","leetcode_13.md":"CrFuqEeW","leetcode_136.md":"D8_ER5x3","leetcode_1367.md":"CigQivMh","leetcode_14.md":"CtIaGChv","leetcode_141.md":"DKBdF-s1","leetcode_143.md":"a8qghDAu","leetcode_144.md":"Dw-vtXiD","leetcode_145.md":"ZFCOgMxP","leetcode_15.md":"DA2gHqsG","leetcode_151.md":"CzUvUUlR","leetcode_153.md":"Dke9uiO6","leetcode_155.md":"AiZx5bGI","leetcode_160.md":"CBKTMHMU","leetcode_17.md":"BSFK_41y","leetcode_175.md":"BcdJ1NdU","leetcode_176.md":"C9t-ILk5","leetcode_181.md":"Dmsp7-Z9","leetcode_182.md":"BT0IaDmF","leetcode_183.md":"Dhtl7gze","leetcode_19.md":"YVk_BVdj","leetcode_192.md":"BUWGF0X4","leetcode_195.md":"DGB-XIST","leetcode_196.md":"D68NQK_-","leetcode_197.md":"ChsnkEE8","leetcode_199.md":"DbB-84g2","leetcode_2.md":"DpB478h6","leetcode_20.md":"mmuwtqpz","leetcode_203.md":"BcQ1xKVy","leetcode_206.md":"Cwq0nl8S","leetcode_21.md":"ZvcndBKp","leetcode_217.md":"DtPSnEWT","leetcode_22.md":"rsJAkeoq","leetcode_222.md":"CR_E3fjv","leetcode_223.md":"DOZpweQT","leetcode_226.md":"908Vag38","leetcode_230.md":"qBPB-Itd","leetcode_235.md":"CyjOtKPo","leetcode_236.md":"BXseTOlM","leetcode_237.md":"DoHzd3SP","leetcode_24.md":"BguPpNTh","leetcode_257.md":"CZAWhWSy","leetcode_26.md":"D_MVIDNs","leetcode_263.md":"DUILNLVd","leetcode_27.md":"CYYX8VNR","leetcode_278.md":"n5Ev7GeB","leetcode_28.md":"oXTYcD7l","leetcode_283.md":"K6eXg45B","leetcode_290.md":"uvnM2S6M","leetcode_292.md":"B_A9wMqx","leetcode_299.md":"CWFGO9wX","leetcode_3.md":"B49HlZ1j","leetcode_303.md":"C3SYa58-","leetcode_31.md":"Db9a0Hrl","leetcode_32.md":"UbmhfUqQ","leetcode_326.md":"cZcoTwX7","leetcode_328.md":"Bo2hyrek","leetcode_33.md":"WP27U6T1","leetcode_34.md":"DrzVfCt8","leetcode_342.md":"BEvA-afC","leetcode_344.md":"q1PpUjLJ","leetcode_345.md":"ptvavmjH","leetcode_35.md":"DnHBXavA","leetcode_36.md":"Cy7PtN5Q","leetcode_38.md":"G4F7PT3M","leetcode_383.md":"uaupvsbq","leetcode_387.md":"CirPaN6L","leetcode_39.md":"Dsa1Y11i","leetcode_4.md":"CCAWzwgm","leetcode_40.md":"B5vvVkzf","leetcode_404.md":"Cd1WMAz1","leetcode_41.md":"N4koYPb6","leetcode_43.md":"CWxjjYn1","leetcode_434.md":"BNlN5B8x","leetcode_445.md":"CDd_mcIw","leetcode_45.md":"CZ-4lKyO","leetcode_46.md":"CyI5DZ3B","leetcode_47.md":"DOnHxxor","leetcode_48.md":"D16-g26T","leetcode_49.md":"CM8PA8ps","leetcode_5.md":"CX8qMbp0","leetcode_50.md":"SnbW1k3s","leetcode_501.md":"CfzrxA0V","leetcode_520.md":"DqjkfZtt","leetcode_53.md":"BWNilhuO","leetcode_54.md":"CZOeMHSs","leetcode_541.md":"DaKjhk_i","leetcode_55.md":"BPDOFar5","leetcode_56.md":"BHlxgw9e","leetcode_57.md":"gvExSXKe","leetcode_58.md":"C8bK4nX3","leetcode_59.md":"BUCybWZ7","leetcode_6.md":"CM-LaKRz","leetcode_60.md":"Bx4mPUZ_","leetcode_61.md":"Ct90X7Xu","leetcode_62.md":"DQqL8f6u","leetcode_63.md":"B3NjMKsT","leetcode_645.md":"BU5hy2T3","leetcode_65.md":"DJ5GPqij","leetcode_66.md":"CvNByAHb","leetcode_67.md":"DeynKHNy","leetcode_68.md":"Bh256SCo","leetcode_69.md":"Ctanodwq","leetcode_690.md":"DNG2eily","leetcode_7.md":"52_IfQ1c","leetcode_70.md":"CojEx3fy","leetcode_704.md":"DmFrwlNs","leetcode_705.md":"CdatKC77","leetcode_706.md":"jaJDLgTf","leetcode_707.md":"D4JrDpIm","leetcode_709.md":"rgDwaHkW","leetcode_71.md":"DWcFQjGp","leetcode_725.md":"CxPSiUv-","leetcode_729.md":"38RgIWzS","leetcode_73.md":"w-0YJ8VZ","leetcode_74.md":"x-SzOTb3","leetcode_75.md":"CeVhdGkp","leetcode_766.md":"BNqhKAYD","leetcode_77.md":"DCNSYueH","leetcode_771.md":"B4m08ah1","leetcode_78.md":"cGtH9nHM","leetcode_781.md":"CBi7CTZa","leetcode_784.md":"E_gzlyj3","leetcode_79.md":"1KAIQadl","leetcode_796.md":"B6-tPY0f","leetcode_8.md":"CiRb_eJV","leetcode_80.md":"EEIPEY-U","leetcode_804.md":"De5X282L","leetcode_806.md":"M8h8fR1P","leetcode_81.md":"BySfgCSj","leetcode_811.md":"BiQYCBQD","leetcode_817.md":"DkwaEHwR","leetcode_82.md":"DBdiDGuN","leetcode_825.md":"DpxXOBE8","leetcode_83.md":"D2SOEAxu","leetcode_830.md":"C_8Ug6R_","leetcode_832.md":"D59G0Vhc","leetcode_835.md":"UGcbehW6","leetcode_840.md":"BWB_z3ZV","leetcode_849.md":"B9orQBfQ","leetcode_86.md":"BJHzF0se","leetcode_867.md":"BtpHDudq","leetcode_876.md":"DWKZa6Qc","leetcode_88.md":"CnAidIJv","leetcode_883.md":"CqRGfiCN","leetcode_884.md":"OgaPBPA8","leetcode_892.md":"CB5y3IJH","leetcode_896.md":"CsFqLqnj","leetcode_9.md":"B-8soFLu","leetcode_92.md":"CkpUMOmY","leetcode_93.md":"Dw2ccnvL","leetcode_94.md":"1OC-RM1S","leetcode_95.md":"BWg_djzX","leetcode_96.md":"DcdyLlMC","leetcode_98.md":"D3AP2u4P","leetcode_99.md":"BbiISS-m","leetcode_index.md":"BRTPPLXX","posts_2015-03-25-older-blogs.md":"DZoxdXye","posts_2015-03-28-building-with-gulp.md":"sdJdNtf6","posts_2015-04-16-dive-into-promise.md":"BEu_TbdI","posts_2015-04-19-css-layout.md":"Bpnt45fz","posts_2015-05-20-dive-into-express-1.md":"C0Ko0zXI","posts_2015-06-16-dive-into-express-2.md":"D0WUzJng","posts_2015-07-16-dive-into-angular-1.md":"D7ynF5Rb","posts_2015-07-16-dive-into-angular-2.md":"Du0O7ZZf","posts_2015-07-17-dive-into-angular-3.md":"DbCIj68Y","posts_2015-07-19-dive-into-angular-4.md":"Db8qdx01","posts_2015-07-21-dive-into-angular-5.md":"BB6GoHE9","posts_2015-07-28-dive-into-angular-6.md":"UEA9Pzll","posts_2015-08-08-dive-into-angular-7.md":"asV3zY8z","posts_2015-08-10-asynchronous-error-handling.md":"Dnf_dQ4W","posts_2015-08-15-webpack-tutorials.md":"BymK1vxe","posts_2015-08-17-node-stream.md":"BkHgUBI9","posts_2015-10-22-express-in-depth.md":"BtNLGh30","posts_2015-11-02-koa-middleware.md":"BbR_3_qV","posts_2015-11-09-gulp-react-task-build.md":"2bpnlBW-","posts_2015-11-29-async-control-flow-1.md":"CSURW6Fa","posts_2015-11-29-async-control-flow-2.md":"oi1cbbtm","posts_2015-11-30-async-control-flow-3.md":"DJeFwDmC","posts_2016-02-01-d3-force-event-conflict.md":"BNRPy7tM","posts_2016-02-29-node-core-buffer.md":"gFqGAgZ-","posts_2016-03-21-flux.md":"CDqe_uBO","posts_2016-03-23-redux-start.md":"DC2SfgZE","posts_2016-03-25-redux-middleware.md":"OgHXyIW0","posts_2016-06-28-network-crawler.md":"DtyoJjfO","posts_2016-07-28-javascript-benchmark.md":"J_DA4oBj","posts_2016-08-10-jstip-always-async-callback.md":"BwbbI5JU","posts_2016-09-02-golang-start.md":"CVv8_Qy9","posts_2016-09-27-node-crypto.md":"BC9-I9Lg","posts_2016-10-17-https.md":"C3a61ODq","posts_2016-11-08-koa2.md":"DnOZng0n","posts_2016-11-30-flex-layout.md":"DzmhMZ1Y","posts_2017-01-10-web-route.md":"DAVC9J1r","posts_2017-02-06-matplotlib-line.md":"pZhZ3LG9","posts_2017-02-07-matplotlib-bar.md":"CVsq2jgg","posts_2017-09-06-stanford-ml-linear-regression.md":"BvWhYQb0","posts_2017-09-08-stanford-ml-logistic-regression.md":"BfaOQAOZ","posts_2017-09-10-stanford-ml-regularization.md":"0-LjQAKl","posts_2017-09-12-stanford-ml-neural-network.md":"Cy3G0bI7","posts_2017-09-14-stanford-ml-k-means.md":"BTHo4YgW","posts_2017-09-14-stanford-ml-svm.md":"DkqhyHk7","posts_2017-09-15-stanford-ml-pca.md":"CEipJCfa","posts_2017-09-20-stanford-ml-advice.md":"DNTaG15K","posts_2017-09-20-stanford-ml-anomaly-detection.md":"BHhRAF0U","posts_2018-02-24-dl-lr.md":"C3Wqmm9O","posts_2018-02-24-dl-nn.md":"DleMdLIq","posts_2018-02-26-dl-tips.md":"3N1VlYo0","posts_2018-02-27-dl-optimizer.md":"lnaZKKN_","posts_2018-03-12-dl-hyperparameter-bn-softmax.md":"DQlLW8RL","posts_2018-03-13-dl-cnn.md":"C5ycZhux","posts_2018-03-15-dl-classical-netoworks.md":"Xf-GiTSJ","posts_2018-03-16-dl-resnet.md":"cDlwSQAo","posts_2018-03-18-dl-inception.md":"BW9UsgWu","posts_2018-03-25-dl-object-detection.md":"_aFjcfuL","posts_2018-04-03-dl-face-recognition.md":"D_lFD9IM","posts_2018-04-03-dl-style-transfer.md":"Rv6G7Dq-","posts_2018-04-10-dl-rnn.md":"C5ySFde2","posts_2018-05-09-dl-nlp.md":"Dy3Gjllr","posts_2018-05-13-dl-seq2seq.md":"CXSz0lxj","posts_2018-05-28-dl-attention-model.md":"CsNUVA27","posts_2018-05-28-dl-speech-rec.md":"CoZwK3xk","posts_2018-05-29-dl-strategy-1.md":"clCw_QDw","posts_2018-05-29-dl-strategy-2.md":"CJQPDi3E","posts_2018-06-26-data-viz.md":"DNEzHzsb","posts_2018-08-10-influxdb-grafana.md":"CcZiK8eZ","posts_2018-12-16-vue-reactive.md":"DBKkTIz6","posts_2019-01-06-k8s-1.md":"eHtAALiM","posts_2019-01-10-k8s-2.md":"D1lwXVC7","posts_2019-01-13-k8s-3.md":"CZih4wtT","posts_2019-01-14-k8s-4.md":"CRISezAE","posts_2019-02-14-k8s-5.md":"CgmHmD1y","posts_2019-02-14-k8s-6.md":"C1sVp0lq","posts_2019-02-16-k8s-7.md":"DG5SPFPy","posts_2019-03-24-k8s-8.md":"D8Esyhto","posts_2019-11-08-servicemesh.md":"D5FgbdsB","posts_2020-01-05-python-decorator-dynamic-args.md":"DThK08x9","posts_2020-03-01-mac-latex.md":"DItGctkH","posts_2020-08-02-go-tips.md":"B5l8CWS9","posts_2020-08-03-cgo.md":"r_EcNVYW","posts_2020-08-22-minimize-docker-image.md":"D3FaLq6d","posts_2020-11-06-doctools.md":"DjjdnsCM","posts_2020-11-27-mysql-db-size.md":"By2vMxnl","posts_2020-12-05-js-formatunicorn.md":"COfkSFRw","posts_2020-12-15-sysdig.md":"Dr7e9JHZ","posts_2021-05-10-go-cross-compiling.md":"C6kCU1Bf","posts_2021-05-16-shell-commands.md":"B2Mc7BeE","posts_2021-05-17-raspberrypi-1.md":"BiJ7vh5Y","posts_2021-05-19-raspberrypi-2.md":"DbHXesiN","posts_2021-05-23-go-customize-marshal.md":"JNvQIsVb","posts_2021-07-18-go-template.md":"DvA1sWtP","posts_2022-11-19-go-embed.md":"m8AIA7yJ","posts_2023-04-19-rust-string.md":"B_lAJh4Q","posts_2023-06-04-goroutine.md":"BWoNlnk2","posts_2025-01-18-ramble.md":"C005Gp6b","posts_2025-01-27-ramble.md":"CuuODeY6","posts_2025-02-08-ramble.md":"Bdq2xI_g","posts_2025-02-11-antlr.md":"qBw-IEi3","posts_index.md":"CbML6XEQ","speeches_index.md":"CCxSlm1y"}
